trdate/__init__.py
trdate/code/__init__.py
trdate/code/date_utils.py
trdate/code/main.py
trdate/code/utils.py
trdate/tests/__init__.py
trdate/tests/test_date_utils.py
trdate/tests/test_main.py
trdate/tests/test_utils.py
trdate-1.0.2.dist-info/LICENSE
trdate-1.0.2.dist-info/METADATA
trdate-1.0.2.dist-info/WHEEL
trdate-1.0.2.dist-info/RECORD
